BinToGray.v
module bintogray (
    input wire[3:0] bin,
    output wire[3:0] gray
);

assign gray[3] = bin[3];
assign gray[2] = bin[3] ^ bin[2];
assign gray[1] = bin[2] ^ bin[1];
assign gray[0] = bin[1] ^ bin[0];

endmodule

BinToGray_tb.v
module bintogray_tb (
);
reg[3:0] bin ;
wire[3:0] gray;
integer i;

bintogray dut(.bin(bin), .gray(gray));

initial begin
    $dumpfile("bintogray.vcd");
    $dumpvars(0,bintogray_tb);
end

initial begin
    bin = 4'b0001;
    $display("Binary Value  |   Gray Value");
    for(i = 0; i<16; i = i +1) begin
        $display("%4b  |    %4b",bin , gray);
        bin = bin + 1;
        #10;
    end
    $finish;
end
    
endmodule

bintogray.vcd
$date
	Mon Oct  6 11:54:00 2025
$end
$version
	Icarus Verilog
$end
$timescale
	1s
$end
$scope module bintogray_tb $end
$var wire 4 ! gray [3:0] $end
$var reg 4 " bin [3:0] $end
$var integer 32 # i [31:0] $end
$scope module dut $end
$var wire 4 $ bin [3:0] $end
$var wire 4 % gray [3:0] $end
$upscope $end
$upscope $end
$enddefinitions $end
$comment Show the parameter values. $end
$dumpall
$end
#0
$dumpvars
b11 %
b10 $
b0 #
b10 "
b11 !
$end
#10
b10 !
b10 %
b11 "
b11 $
b1 #
#20
b110 !
b110 %
b100 "
b100 $
b10 #
#30
b111 !
b111 %
b101 "
b101 $
b11 #
#40
b101 !
b101 %
b110 "
b110 $
b100 #
#50
b100 !
b100 %
b111 "
b111 $
b101 #
#60
b1100 !
b1100 %
b1000 "
b1000 $
b110 #
#70
b1101 !
b1101 %
b1001 "
b1001 $
b111 #
#80
b1111 !
b1111 %
b1010 "
b1010 $
b1000 #
#90
b1110 !
b1110 %
b1011 "
b1011 $
b1001 #
#100
b1010 !
b1010 %
b1100 "
b1100 $
b1010 #
#110
b1011 !
b1011 %
b1101 "
b1101 $
b1011 #
#120
b1001 !
b1001 %
b1110 "
b1110 $
b1100 #
#130
b1000 !
b1000 %
b1111 "
b1111 $
b1101 #
#140
b0 !
b0 %
b0 "
b0 $
b1110 #
#150
b1 !
b1 %
b1 "
b1 $
b1111 #
#160
b10000 #
