Comparator.v
module comparator(input wire[3:0] A, B, output reg equal, less_than, greater_than);
always @(A,B) begin 
    if(A == B) begin 
        equal = 1'b1;
        less_than = 1'b0;
        greater_than  = 1'b0;
    end
    else if (A > B) begin 
        greater_than  = 1'b1;
        less_than = 1'b0;
        equal = 1'b0;
    end
    else begin
        less_than = 1'b1;
        greater_than = 1'b0;
        equal = 1'b0;
    end
end

endmodule

Comparator_tb.v
module comparator_tb ();
    reg[3:0] A, B;
    wire equal, less_than, greater_than;
    comparator dut(.A(A), .B(B), .equal(equal), .less_than(less_than), .greater_than(greater_than));

    initial begin
        $dumpfile("comparator.vcd");
        $dumpvars(0,comparator_tb);
    end
    initial begin
        $monitor("t = %8t, A = %b, B = %b, Equal = %b, Less_than = %b, Greater_than = %b",$time, A, B, equal, less_than, greater_than);
        #10 A = 4'b000; B = 4'b0000;
        #10 A = 4'b1000; B = 4'b1000;
        #10 A = 4'b1000; B = 4'b0100;
        #10 A = 4'b1001; B = 4'b1010;
        #10 A = 4'b0100; B = 4'b0001;
        #10 A = 4'b010; B = 4'b0110;
        #10 A = 4'b1111; B = 4'b1100;
        #10 $finish;
    end

endmodule

comparator.vcd
$date
	Sun Oct 19 23:44:26 2025
$end
$version
	Icarus Verilog
$end
$timescale
	1s
$end
$scope module comparator_tb $end
$var wire 1 ! less_than $end
$var wire 1 " greater_than $end
$var wire 1 # equal $end
$var reg 4 $ A [3:0] $end
$var reg 4 % B [3:0] $end
$scope module dut $end
$var wire 4 & A [3:0] $end
$var wire 4 ' B [3:0] $end
$var reg 1 # equal $end
$var reg 1 " greater_than $end
$var reg 1 ! less_than $end
$upscope $end
$upscope $end
$enddefinitions $end
$comment Show the parameter values. $end
$dumpall
$end
#0
$dumpvars
bx '
bx &
bx %
bx $
x#
x"
x!
$end
#10
0"
0!
1#
b0 %
b0 '
b0 $
b0 &
#20
b1000 %
b1000 '
b1000 $
b1000 &
#30
0#
1"
b100 %
b100 '
#40
0"
1!
b1010 %
b1010 '
b1001 $
b1001 &
#50
0!
1"
b1 %
b1 '
b100 $
b100 &
#60
0"
1!
b110 %
b110 '
b10 $
b10 &
#70
0!
1"
b1100 %
b1100 '
b1111 $
b1111 &
