RippleCarryAdder.v
`timescale 1ps/1ps

module ripplecarryadder_4bit (
    input wire[3:0] a, b,
    input wire Cin,
    output wire[3:0] Sum, 
    output wire Cout
);

wire[2:0] w;

fulladder a1(.A(a[0]), .B(b[0]), .Cin(Cin),  .Cout(w[0]), .Sum(Sum[0]));
fulladder a2(.A(a[1]), .B(b[1]), .Cin(w[0]), .Cout(w[1]), .Sum(Sum[1]));
fulladder a3(.A(a[2]), .B(b[2]), .Cin(w[1]), .Cout(w[2]), .Sum(Sum[2]));
fulladder a4(.A(a[3]), .B(b[3]), .Cin(w[2]), .Cout(Cout), .Sum(Sum[3]));
    
endmodule


module fulladder (
    input wire A, B, Cin,
    output wire Cout, Sum
);

assign Cout = (A & B) | (B & Cin) | (A & Cin);
assign Sum  = A^B^Cin;
    
endmodule

FullAdder_tb.v
module fulladder_tb ();
reg A, B, Cin;
wire Cout, Sum;

fulladder uut(.A(A), .B(B), .Cin(Cin), .Cout(Cout), .Sum(Sum));

initial begin
    $dumpfile("fulladder.vcd");
    $dumpvars(0,fulladder_tb);
end

initial begin
    $monitor("t = %2d, A = %b, B = %b, Cin = %b, Cout = %b, Sum = %b", $time, A, B, Cin, Cout, Sum);
    A = 1'b0; B = 1'b0; Cin = 1'b0;
    #10 A = 1'b0; B = 1'b0; Cin = 1'b1;
    #10 A = 1'b0; B = 1'b1; Cin = 1'b0;
    #10 A = 1'b0; B = 1'b1; Cin = 1'b1;
    #10 A = 1'b1; B = 1'b0; Cin = 1'b0;
    #10 A = 1'b1; B = 1'b0; Cin = 1'b1;
    #10 A = 1'b1; B = 1'b1; Cin = 1'b0;
    #10 A = 1'b1; B = 1'b1; Cin = 1'b1;
    #10 $finish;
end

endmodule

fulladder.vcd
$date
	Fri Oct  3 22:54:03 2025
$end
$version
	Icarus Verilog
$end
$timescale
	1s
$end
$scope module fulladder_tb $end
$var wire 1 ! Sum $end
$var wire 1 " Cout $end
$var reg 1 # A $end
$var reg 1 $ B $end
$var reg 1 % Cin $end
$scope module uut $end
$var wire 1 # A $end
$var wire 1 $ B $end
$var wire 1 % Cin $end
$var wire 1 " Cout $end
$var wire 1 ! Sum $end
$upscope $end
$upscope $end
$enddefinitions $end
$comment Show the parameter values. $end
$dumpall
$end
#0
$dumpvars
0%
0$
0#
0"
0!
$end
#10
1!
1%
#20
0%
1$
#30
1"
0!
1%
#40
0"
1!
0%
0$
1#
#50
1"
0!
1%
#60
0%
1$
#70
1!
1%
