GrayToBin.v
module graytobin (
    input wire[3:0] gray,
    output wire[3:0] bin
);

assign bin[3] = gray[3];
assign bin[2] = bin[3] ^ gray[2]; 
assign bin[1] = bin[2] ^ gray[1]; 
assign bin[0] = bin[1] ^ gray[0]; 
    
endmodule

GrayToBin_tb.v
module graytobin_tb ();
    reg[3:0] gray;
    wire[3:0] bin;
    integer i;

    graytobin dut(.gray(gray), .bin(bin));

    initial begin
        $dumpfile("graytobin.vcd");
        $dumpvars(0,graytobin_tb);
    end

    initial begin
        gray = 4'b0000;
        #10;
        $display("Gray Value  |   Binary Value", gray, bin);
        for(i = 0; i<16; i = i + 1) begin
             $display("%4b  |    %4b",gray , bin);
            gray = gray + 1;
            #10;
        end
        $finish;
    end
endmodule

graytobin.vcd
$date
	Tue Oct  7 11:31:32 2025
$end
$version
	Icarus Verilog
$end
$timescale
	1s
$end
$scope module graytobin_tb $end
$var wire 4 ! bin [3:0] $end
$var reg 4 " gray [3:0] $end
$var integer 32 # i [31:0] $end
$scope module dut $end
$var wire 4 $ gray [3:0] $end
$var wire 4 % bin [3:0] $end
$upscope $end
$upscope $end
$enddefinitions $end
$comment Show the parameter values. $end
$dumpall
$end
#0
$dumpvars
b0 %
b0 $
bx #
b0 "
b0 !
$end
#10
b1 !
b1 %
b1 "
b1 $
b0 #
#20
b11 !
b11 %
b10 "
b10 $
b1 #
#30
b10 !
b10 %
b11 "
b11 $
b10 #
#40
b111 !
b111 %
b100 "
b100 $
b11 #
#50
b110 !
b110 %
b101 "
b101 $
b100 #
#60
b100 !
b100 %
b110 "
b110 $
b101 #
#70
b101 !
b101 %
b111 "
b111 $
b110 #
#80
b1111 !
b1111 %
b1000 "
b1000 $
b111 #
#90
b1110 !
b1110 %
b1001 "
b1001 $
b1000 #
#100
b1100 !
b1100 %
b1010 "
b1010 $
b1001 #
#110
b1101 !
b1101 %
b1011 "
b1011 $
b1010 #
#120
b1000 !
b1000 %
b1100 "
b1100 $
b1011 #
#130
b1001 !
b1001 %
b1101 "
b1101 $
b1100 #
#140
b1011 !
b1011 %
b1110 "
b1110 $
b1101 #
#150
b1010 !
b1010 %
b1111 "
b1111 $
b1110 #
#160
b0 !
b0 %
b0 "
b0 $
b1111 #
#170
b10000 #
