PISO.v
`timescale 1ns/1ps

module piso (
    input clk, rst, load,
    input wire[ 3:0] parallel_in,
    output serial_out
 );

 reg[3:0] shift_reg;

 always @(posedge clk or posedge rst) begin
    if (rst) begin
        shift_reg <=4'b0000;
    end
    else if (load) begin
        shift_reg <= parallel_in;
    end
    else begin
        shift_reg <= {1'b0,shift_reg[3:1]};
    end
 end

 assign serial_out = shift_reg[0];
    
endmodule

PISO_tb.v
`timescale 1ns/1ps

module piso_tb ();
    reg clk, rst, load;
    reg[3:0] parallel_in;
    wire serial_out;

    piso dut(.clk(clk), .rst(rst), .load(load), .parallel_in(parallel_in), .serial_out(serial_out));

    initial begin
        $dumpfile("piso.vcd");
        $dumpvars(0,piso_tb);
    end

    initial begin
        clk = 1'b0;
        forever begin
            #5 clk = ~clk;
        end
    end

    initial begin
        $monitor("t = %8t, CLK = %b, RST = %b, LOAD = %b, Parallel_in = %4b, Serial_out = %b", $time, clk, rst, load, parallel_in, serial_out);
        #10 rst = 1; load = 0; parallel_in = 4'b0000;
        #10 rst = 0;

        load = 1; parallel_in = 4'b1011; #10;
        load = 0;
        #50;
        $finish;
    end
endmodule

piso.vcd
$date
	Fri Oct 24 23:37:15 2025
$end
$version
	Icarus Verilog
$end
$timescale
	1ps
$end
$scope module piso_tb $end
$var wire 1 ! serial_out $end
$var reg 1 " clk $end
$var reg 1 # load $end
$var reg 4 $ parallel_in [3:0] $end
$var reg 1 % rst $end
$scope module dut $end
$var wire 1 " clk $end
$var wire 1 # load $end
$var wire 4 & parallel_in [3:0] $end
$var wire 1 % rst $end
$var wire 1 ! serial_out $end
$var reg 4 ' shift_reg [3:0] $end
$upscope $end
$upscope $end
$enddefinitions $end
$comment Show the parameter values. $end
$dumpall
$end
#0
$dumpvars
bx '
bx &
x%
bx $
x#
0"
x!
$end
#5000
b0xxx '
1"
#10000
0!
b0 '
0"
b0 $
b0 &
0#
1%
#15000
1"
#20000
0"
b1011 $
b1011 &
1#
0%
#25000
1!
b1011 '
1"
#30000
0"
0#
#35000
b101 '
1"
#40000
0"
#45000
0!
b10 '
1"
#50000
0"
#55000
1!
b1 '
1"
#60000
0"
#65000
0!
b0 '
1"
