SIPO.v
module sipo (
    input clk, rst, serial_in,
    output wire[3:0] parallel_out
);

reg[3:0] serial_reg;

always @(posedge clk) begin
    if (rst == 1'b1) begin
        serial_reg = 4'b0000;
    end
    else begin
        serial_reg[0] <= serial_in;
        serial_reg[1] <= serial_reg[0];
        serial_reg[2] <= serial_reg[1];
        serial_reg[3] <= serial_reg[2];
    end
    
end

assign parallel_out = serial_reg;
    
endmodule   

/*
// 4-bit Serial In Parallel Out Shift Register
module SIPO (
    input clk,
    input rst,
    input serial_in,
    output [3:0] parallel_out
);
    reg [3:0] shift_reg;

    always @(posedge clk or posedge rst) begin
        if (rst)
            shift_reg <= 4'b0000;
        else
            shift_reg <= {shift_reg[2:0], serial_in};
    end

    assign parallel_out = shift_reg;
endmodule
*/

SIPO_tb.v
module sipo_tb ();
    reg clk, rst, serial_in;
    wire[3:0] parallel_out;

    sipo dut(.clk(clk), .rst(rst), .serial_in(serial_in), .parallel_out(parallel_out));

    initial begin
        $dumpfile("sipo.vcd");
        $dumpvars(0,sipo_tb);
    end

    initial begin
        clk = 1'b0;
        forever begin
            #5 clk = ~clk;
        end
    end

    initial begin
        $monitor("t = %8t, CLK = %b, RST = %b, Serial_in = %b, Parallel_out = %4b", $time, clk, rst, serial_in, parallel_out);
        #10 serial_in = 0; rst = 1'b1;
        #10 serial_in = 0; rst = 1'b0;
        #10 serial_in = 1; rst = 1'b0;
        #10 serial_in = 0; rst = 1'b0;
        #10 serial_in = 1; rst = 1'b0;
        #10 serial_in = 0; rst = 1'b1;
        #10 $finish;
        
    end

endmodule

sipo.vcd
$date
	Fri Oct 24 23:35:53 2025
$end
$version
	Icarus Verilog
$end
$timescale
	1s
$end
$scope module sipo_tb $end
$var wire 4 ! parallel_out [3:0] $end
$var reg 1 " clk $end
$var reg 1 # rst $end
$var reg 1 $ serial_in $end
$scope module dut $end
$var wire 1 " clk $end
$var wire 4 % parallel_out [3:0] $end
$var wire 1 # rst $end
$var wire 1 $ serial_in $end
$var reg 4 & serial_reg [3:0] $end
$upscope $end
$upscope $end
$enddefinitions $end
$comment Show the parameter values. $end
$dumpall
$end
#0
$dumpvars
bx &
bx %
x$
x#
0"
bx !
$end
#5
1"
#10
0"
1#
0$
#15
b0 !
b0 %
b0 &
1"
#20
0"
0#
#25
1"
#30
0"
1$
#35
b1 !
b1 %
b1 &
1"
#40
0"
0$
#45
b10 !
b10 %
b10 &
1"
#50
0"
1$
#55
b101 !
b101 %
b101 &
1"
#60
0"
1#
0$
#65
b0 !
b0 %
b0 &
1"
