SISO.v
module siso (
    input clk, Rst,
    input serial_in,
    output reg serial_out
);
    reg B, C, D;

    always @(posedge clk, posedge Rst) begin
        if(Rst == 1'b1) begin
            serial_out = 1'b0;
            B <= 1'b0;
            C <= 1'b0;
            D <= 1'b0;
        end
        else begin
            serial_out = B;
            B <= C;
            C <= D;
            D <= serial_in;
            
        end
    end
endmodule

SISO_tb.v
module siso_tb ();
  reg serial_in, clk, Rst;
  wire serial_out;

  siso dut(.clk(clk), .Rst(Rst), .serial_in(serial_in), .serial_out(serial_out));

  initial begin
    $dumpfile("siso.vcd");
    $dumpvars(0,siso_tb);

  end

  initial begin
    clk = 1'b0;
    forever begin
        #5 clk = ~clk;
    end
  end


    initial begin
        $monitor("t = %8t, CLK =%b, RST = %b, Serial_IN = %b, Serial_out = %b", $time, clk, Rst, serial_in, serial_out);
        Rst = 1'b1; serial_in = 1'b0;
        #12 Rst = 1'b0;       // Release reset after a bit
        #10 serial_in = 1'b1;
        #10 serial_in = 1'b0;
        #10 serial_in = 1'b1;
        #40 $finish;
        end

    
endmodule

siso.vcd
$date
	Tue Oct 21 00:05:24 2025
$end
$version
	Icarus Verilog
$end
$timescale
	1s
$end
$scope module siso_tb $end
$var wire 1 ! serial_out $end
$var reg 1 " Rst $end
$var reg 1 # clk $end
$var reg 1 $ serial_in $end
$scope module dut $end
$var wire 1 " Rst $end
$var wire 1 # clk $end
$var wire 1 $ serial_in $end
$var reg 1 % B $end
$var reg 1 & C $end
$var reg 1 ' D $end
$var reg 1 ! serial_out $end
$upscope $end
$upscope $end
$enddefinitions $end
$comment Show the parameter values. $end
$dumpall
$end
#0
$dumpvars
0'
0&
0%
0$
0#
1"
0!
$end
#5
1#
#10
0#
#12
0"
#15
1#
#20
0#
#22
1$
#25
1'
1#
#30
0#
#32
0$
#35
0'
1&
1#
#40
0#
#42
1$
#45
1'
0&
1%
1#
#50
0#
#55
1&
0%
1!
1#
#60
0#
#65
1%
0!
1#
#70
0#
#75
1!
1#
