TFF.v
module tff (
    input clk, reset, t,
    output reg q
);

always @(posedge clk) begin
    if(reset) begin
        q <= 1'b0;
    end
    else q <= ~t;
end
    
endmodule

TFF_tb.v
module tff_tb ();
    reg clk, reset, t;
    wire q;

    tff dut(.clk(clk), .reset(reset), .t(t), .q(q));

    initial begin
        clk = 1'b0;
        forever begin
            #5 clk = ~clk;
        end
    end

    initial begin
        $dumpfile("tff.vcd");
        $dumpvars(0,tff_tb);
    end
    initial begin
        $monitor("t = %8t, CLK = %b, reset = %b, t = %b, q = %b", $time, clk, reset, t, q);
        #10 t = 1'b0; reset = 0;
        #10 t = 1'b1; reset = 1;
        #10 t = 1'b1; reset = 0;
        #10 t = 1'b0; reset = 0;
        #10 $finish;
    end
endmodule

tff.vcd
$date
	Sat Oct 18 23:46:10 2025
$end
$version
	Icarus Verilog
$end
$timescale
	1s
$end
$scope module tff_tb $end
$var wire 1 ! q $end
$var reg 1 " clk $end
$var reg 1 # reset $end
$var reg 1 $ t $end
$scope module dut $end
$var wire 1 " clk $end
$var wire 1 # reset $end
$var wire 1 $ t $end
$var reg 1 ! q $end
$upscope $end
$upscope $end
$enddefinitions $end
$comment Show the parameter values. $end
$dumpall
$end
#0
$dumpvars
x$
x#
0"
x!
$end
#5
1"
#10
0"
0#
0$
#15
1!
1"
#20
0"
1#
1$
#25
0!
1"
#30
0"
0#
#35
1"
#40
0"
0$
#45
1!
1"
